nori/bind.pyi
nori/__init__.py
nori/bind.so
nori/dictionary/latest-userdict.txt
nori/dictionary/latest-dictionary.nori
nori_clone-1.0.0.dist-info/LICENSE
nori_clone-1.0.0.dist-info/METADATA
nori_clone-1.0.0.dist-info/top_level.txt
nori_clone-1.0.0.dist-info/RECORD
nori_clone-1.0.0.dist-info/WHEEL
